Metadata-Version: 2.4
Name: adafruit-circuitpython-aws-iot
Version: 3.0.3
Summary: Amazon AWS IoT MQTT Client for CircuitPython
Author-email: Adafruit Industries <circuitpython@adafruit.com>
License: MIT
Project-URL: Homepage, https://github.com/adafruit/Adafruit_CircuitPython_AWS_IOT
Keywords: adafruit,blinka,circuitpython,micropython,aws_iot,aws,,iot,,amazon,,mqtt,,client
Classifier: Intended Audience :: Developers
Classifier: Topic :: Software Development :: Libraries
Classifier: Topic :: Software Development :: Embedded Systems
Classifier: Topic :: System :: Hardware
Classifier: License :: OSI Approved :: MIT License
Classifier: Programming Language :: Python :: 3
License-File: LICENSE
Requires-Dist: Adafruit-Blinka
Requires-Dist: adafruit-circuitpython-minimqtt
Provides-Extra: optional
Dynamic: license-file
